[
  {
    "text": "Bunu bilmeden ev almayın!",
    "category": "Tüyolar & Hatalar"
  },
  {
    "text": "2026'da emlak piyasasında sizi neler bekliyor?",
    "category": "Piyasa & Haberler"
  },
  {
    "text": "Sadece 100 bin TL ile nasıl yatırım yapılır?",
    "category": "Yatırım & Kazanç"
  },
  {
    "text": "Ev satarken yapılan en büyük 3 hata!",
    "category": "Tüyolar & Hatalar"
  },
  {
    "text": "Beylikdüzü'nün en hızlı değerlenen 3 bölgesi!",
    "category": "Beylikdüzü & Yerel"
  },
  {
    "text": "Kiracınızla sorun yaşıyorsanız bu videoyu izleyin.",
    "category": "Tüyolar & Hatalar"
  },
  {
    "text": "Tapu devrinde dolandırılmamak için dikkat!",
    "category": "Tüyolar & Hatalar"
  },
  {
    "text": "Evinizin değerini %20 artırmanın yolu!",
    "category": "Tüyolar & Hatalar"
  },
  {
    "text": "Neden emlak danışmanıyla çalışmalısınız?",
    "category": "Tüyolar & Hatalar"
  },
  {
    "text": "Yatırımlık daire ararken bakmanız gereken 3 şey.",
    "category": "Yatırım & Kazanç"
  },
  {
    "text": "Faizler düşerken ev alınır mı?",
    "category": "Piyasa & Haberler"
  },
  {
    "text": "Kira artış oranlarında son durum ne?",
    "category": "Tüyolar & Hatalar"
  },
  {
    "text": "Ekspertiz raporunda gizli tehlikeler!",
    "category": "Piyasa & Haberler"
  },
  {
    "text": "Acil satılık ilanlarındaki gerçekler.",
    "category": "Hızlı & Pratik"
  },
  {
    "text": "Emlak vergisi hakkında bilmeniz gerekenler.",
    "category": "Piyasa & Haberler"
  },
  {
    "text": "Yabancıya konut satışı bitti mi?",
    "category": "Tüyolar & Hatalar"
  },
  {
    "text": "Arsa yatırımı mı, daire yatırımı mı?",
    "category": "Yatırım & Kazanç"
  },
  {
    "text": "Dükkan yatırımı yapmadan önce durun!",
    "category": "Yatırım & Kazanç"
  },
  {
    "text": "Kat mülkiyeti ile kat irtifakı farkı nedir?",
    "category": "Tüyolar & Hatalar"
  },
  {
    "text": "Ev alırken belediyede bakmanız gereken evraklar.",
    "category": "Tüyolar & Hatalar"
  },
  {
    "text": "Rayiç bedel oyununa gelmeyin!",
    "category": "Tüyolar & Hatalar"
  },
  {
    "text": "Sahibinden ilanlardaki gizli riskler.",
    "category": "Tüyolar & Hatalar"
  },
  {
    "text": "Lansman fiyatıyla ev almak karlı mı?",
    "category": "Yatırım & Kazanç"
  },
  {
    "text": "Kentsel dönüşümde hakkınızı biliyor musunuz?",
    "category": "Tüyolar & Hatalar"
  },
  {
    "text": "Hisseli tapu alırken dikkat etmeniz gereken 1 kural.",
    "category": "Tüyolar & Hatalar"
  },
  {
    "text": "İpotekli ev nasıl satılır?",
    "category": "Tüyolar & Hatalar"
  },
  {
    "text": "İskanı olmayan ev alınır mı?",
    "category": "Tüyolar & Hatalar"
  },
  {
    "text": "Müstakil bir hayat hayal mi?",
    "category": "Tüyolar & Hatalar"
  },
  {
    "text": "Prefabrik ev yatırımı mantıklı mı?",
    "category": "Yatırım & Kazanç"
  },
  {
    "text": "Tiny House yasakları kapıda mı?",
    "category": "Tüyolar & Hatalar"
  },
  {
    "text": "Deniz manzaralı evlerdeki en büyük sorun.",
    "category": "Lüks & Prestij"
  },
  {
    "text": "Metroya yakın ev her zaman kazandırır mı?",
    "category": "Tüyolar & Hatalar"
  },
  {
    "text": "Okul bölgesinde ev almanın avantajları.",
    "category": "Tüyolar & Hatalar"
  },
  {
    "text": "Site içi mi, apartman dairesi mi?",
    "category": "Tüyolar & Hatalar"
  },
  {
    "text": "Güney cephe evin yakıt tasarrufu ne kadar?",
    "category": "Tüyolar & Hatalar"
  },
  {
    "text": "Evinizdeki rutubetten kurtulmanın maliyeti.",
    "category": "Yatırım & Kazanç"
  },
  {
    "text": "Deprem yönetmeliğine uygun ev nasıl anlaşılır?",
    "category": "Tüyolar & Hatalar"
  },
  {
    "text": "Emlak endeksi neyi gösteriyor?",
    "category": "Piyasa & Haberler"
  },
  {
    "text": "Ticari gayrimenkulde amortisman süresi.",
    "category": "Yatırım & Kazanç"
  },
  {
    "text": "Airbnb yatırımı için en iyi bölgeler.",
    "category": "Yatırım & Kazanç"
  },
  {
    "text": "Turistik bölgelerde emlak fırsatları.",
    "category": "Tüyolar & Hatalar"
  },
  {
    "text": "Tarla alırken sit alanlarına dikkat!",
    "category": "Tüyolar & Hatalar"
  },
  {
    "text": "Zeytinlik yatırımı hala mantıklı mı?",
    "category": "Yatırım & Kazanç"
  },
  {
    "text": "Eski bir evi yenileyip satmak (Fixer Upper).",
    "category": "Tüyolar & Hatalar"
  },
  {
    "text": "Lüks konut piyasasında daralma mı var?",
    "category": "Lüks & Prestij"
  },
  {
    "text": "Rezidans yaşamının gizli masrafları.",
    "category": "Lüks & Prestij"
  },
  {
    "text": "Aidatların ev fiyatına etkisi.",
    "category": "Tüyolar & Hatalar"
  },
  {
    "text": "Emlak danışmanına sorulması gereken 5 soru.",
    "category": "Tüyolar & Hatalar"
  },
  {
    "text": "Alıcıların en çok vazgeçme sebebi.",
    "category": "Tüyolar & Hatalar"
  },
  {
    "text": "Satış kapamada en etkili cümleler.",
    "category": "Tüyolar & Hatalar"
  },
  {
    "text": "Emlak videoları neden izlenmiyor?",
    "category": "Tüyolar & Hatalar"
  },
  {
    "text": "Instagram'da emlakçıların yaptığı hatalar.",
    "category": "Tüyolar & Hatalar"
  },
  {
    "text": "LinkedIn emlakçıları için altın kurallar.",
    "category": "Tüyolar & Hatalar"
  },
  {
    "text": "Video kapağınız tıklanmıyorsa bu yüzden.",
    "category": "Tüyolar & Hatalar"
  },
  {
    "text": "Açıklama kısmına hashtag yazmalı mısınız?",
    "category": "Tüyolar & Hatalar"
  },
  {
    "text": "Konut kredisi yapılandırma nasıl yapılır?",
    "category": "Piyasa & Haberler"
  },
  {
    "text": "Peşinatsız ev sahibi olmak mümkün mü?",
    "category": "Tüyolar & Hatalar"
  },
  {
    "text": "Tasarruf finansman şirketlerine güvenilir mi?",
    "category": "Tüyolar & Hatalar"
  },
  {
    "text": "Borçlu ev satışı nasıl gerçekleşir?",
    "category": "Tüyolar & Hatalar"
  },
  {
    "text": "Vefat eden birinin evi nasıl satılır?",
    "category": "Tüyolar & Hatalar"
  },
  {
    "text": "İzale-i Şuyu davası nedir?",
    "category": "Tüyolar & Hatalar"
  },
  {
    "text": "Şufa hakkı başınızı ağrıtabilir!",
    "category": "Tüyolar & Hatalar"
  },
  {
    "text": "Evinizin fotoğrafları neden kötü çıkıyor?",
    "category": "Tüyolar & Hatalar"
  },
  {
    "text": "Emlak ilanlarında 'fırsat' kelimesinin büyüsü.",
    "category": "Tüyolar & Hatalar"
  },
  {
    "text": "Pazar analizi yapmadan fiyat koymayın!",
    "category": "Tüyolar & Hatalar"
  },
  {
    "text": "Evinizin ekspertiz değerini öğrenin.",
    "category": "Tüyolar & Hatalar"
  },
  {
    "text": "Emlak ofisleri neden sözleşme ister?",
    "category": "Tüyolar & Hatalar"
  },
  {
    "text": "Tek yetkili emlakçıyla çalışmanın 5 faydası.",
    "category": "Tüyolar & Hatalar"
  },
  {
    "text": "Emlak komisyonu ne kadar olmalı?",
    "category": "Tüyolar & Hatalar"
  },
  {
    "text": "Kapora yakma durumlarında hukuk ne diyor?",
    "category": "Tüyolar & Hatalar"
  },
  {
    "text": "Ev gezerken yanınızda bulundurmanız gerekenler.",
    "category": "Tüyolar & Hatalar"
  },
  {
    "text": "Karanlık odayı nasıl aydınlatırsınız?",
    "category": "Tüyolar & Hatalar"
  },
  {
    "text": "Eski mutfağı ucuza yenileme rehberi.",
    "category": "Hızlı & Pratik"
  },
  {
    "text": "Zemin katta ev almanın avantajları.",
    "category": "Tüyolar & Hatalar"
  },
  {
    "text": "Çatı katı dairelerin yalıtım sorunu.",
    "category": "Tüyolar & Hatalar"
  },
  {
    "text": "Emlak yatırımı için yaş sınırı var mı?",
    "category": "Yatırım & Kazanç"
  },
  {
    "text": "Emeklilikte emlak yatırımıyla pasif gelir.",
    "category": "Yatırım & Kazanç"
  },
  {
    "text": "Genç yatırımcılar için başlangıç rehberi.",
    "category": "Yatırım & Kazanç"
  },
  {
    "text": "Emlak piyasasında kriz fırsata döner mi?",
    "category": "Piyasa & Haberler"
  },
  {
    "text": "Nakit paranızı emlakta nasıl korursunuz?",
    "category": "Yatırım & Kazanç"
  },
  {
    "text": "Enflasyon karşısında emlak kalkanı.",
    "category": "Yatırım & Kazanç"
  },
  {
    "text": "Geleceğin parlayan emlak bölgeleri.",
    "category": "Tüyolar & Hatalar"
  },
  {
    "text": "Kanal İstanbul güzergahında arsa durumu.",
    "category": "Tüyolar & Hatalar"
  },
  {
    "text": "Bodrum'da kışlık ev almak mantıklı mı?",
    "category": "Tüyolar & Hatalar"
  },
  {
    "text": "Kıbrıs emlak piyasasında büyük fırsat.",
    "category": "Piyasa & Haberler"
  },
  {
    "text": "Yurtdışında ev sahibi olmanın yolları.",
    "category": "Tüyolar & Hatalar"
  },
  {
    "text": "Almanya'da ev fiyatları neden düşüyor?",
    "category": "Tüyolar & Hatalar"
  },
  {
    "text": "Emlakçıların kullandığı özel terimler.",
    "category": "Tüyolar & Hatalar"
  },
  {
    "text": "Tapu üzerindeki şerh nasıl kaldırılır?",
    "category": "Tüyolar & Hatalar"
  },
  {
    "text": "Hacizli gayrimenkul almanın riskleri.",
    "category": "Tüyolar & Hatalar"
  },
  {
    "text": "İhale ile ev almak karlı mı?",
    "category": "Yatırım & Kazanç"
  },
  {
    "text": "Emlak dron çekimlerinin satışa etkisi.",
    "category": "Lüks & Prestij"
  },
  {
    "text": "Virtual Staging ile evi mobilyalı göstermek.",
    "category": "Lüks & Prestij"
  },
  {
    "text": "Evinizde kedi-köpek beslemek satışı zorlaştırır mı?",
    "category": "Tüyolar & Hatalar"
  },
  {
    "text": "Evin havasını değiştirecek 3 küçük dokunuş.",
    "category": "Hızlı & Pratik"
  },
  {
    "text": "İlk izlenim: Evin kapısından girerken.",
    "category": "Tüyolar & Hatalar"
  },
  {
    "text": "Açık hava alanlarının ev değerine katkısı.",
    "category": "Tüyolar & Hatalar"
  },
  {
    "text": "Neden her emlakçı profesyonel değildir?",
    "category": "Tüyolar & Hatalar"
  },
  {
    "text": "Gayrimenkulde güvenin adresi nasıl olunur?",
    "category": "Tüyolar & Hatalar"
  },
  {
    "text": "RE/MAX ile çalışmanın global gücü.",
    "category": "Tüyolar & Hatalar"
  },
  {
    "text": "Beylikdüzü'nde kira garantili yatırımın sırrı!",
    "category": "Beylikdüzü & Yerel"
  },
  {
    "text": "2026'da bu bölge %50 değerlenecek!",
    "category": "Piyasa & Haberler"
  },
  {
    "text": "Evinizi satmadan önce bu 5 tadilatı yapın.",
    "category": "Tüyolar & Hatalar"
  },
  {
    "text": "Emlak piyasasında 'ölü' fiyat yakalama taktiği.",
    "category": "Piyasa & Haberler"
  },
  {
    "text": "Neden her yeni proje iyi bir yatırım değildir?",
    "category": "Yatırım & Kazanç"
  },
  {
    "text": "Tapu harcını kim öder? Kanun ne diyor?",
    "category": "Piyasa & Haberler"
  },
  {
    "text": "Düşük faizli kredi için bankaların gizli şartları.",
    "category": "Piyasa & Haberler"
  },
  {
    "text": "Beylikdüzü Metrobüs hattına en yakın projeler.",
    "category": "Beylikdüzü & Yerel"
  },
  {
    "text": "Evinizdeki gereksiz eşyalar satışı %30 yavaşlatıyor!",
    "category": "Tüyolar & Hatalar"
  },
  {
    "text": "Gayrimenkulde pasif gelir elde etmenin 3 yolu.",
    "category": "Yatırım & Kazanç"
  },
  {
    "text": "Arsa alırken imar durumunda bu kodu kontrol edin.",
    "category": "Tüyolar & Hatalar"
  },
  {
    "text": "İstanbul'da hala 2 milyona ev var mı?",
    "category": "Tüyolar & Hatalar"
  },
  {
    "text": "Emlak danışmanları bu bölgeleri kendilerine saklıyor!",
    "category": "Tüyolar & Hatalar"
  },
  {
    "text": "Kat irtifaklı tapu alırken riskleri biliyor musunuz?",
    "category": "Tüyolar & Hatalar"
  },
  {
    "text": "Kira geliriyle kredi taksiti ödemek hayal mi?",
    "category": "Piyasa & Haberler"
  },
  {
    "text": "Evinizin değerini düşüren 10 kritik hata.",
    "category": "Tüyolar & Hatalar"
  },
  {
    "text": "Sahibinden satılık ilanlarında dolandırıcılık belirtileri.",
    "category": "Tüyolar & Hatalar"
  },
  {
    "text": "Emlak endeksi neden her zaman doğruyu söylemez?",
    "category": "Piyasa & Haberler"
  },
  {
    "text": "Beylikdüzü'nde denize nazır en uygun bölgeler.",
    "category": "Beylikdüzü & Yerel"
  },
  {
    "text": "Yatırım sepetinde neden mutlaka gayrimenkul olmalı?",
    "category": "Yatırım & Kazanç"
  },
  {
    "text": "Deprem sonrası Beylikdüzü'nde talep nasıl değişti?",
    "category": "Beylikdüzü & Yerel"
  },
  {
    "text": "Evinizin banyosunu yenilemek satışı hızlandırır mı?",
    "category": "Hızlı & Pratik"
  },
  {
    "text": "Kentsel dönüşümde mülk sahiplerinin yasal hakları.",
    "category": "Piyasa & Haberler"
  },
  {
    "text": "Emlak piyasasında 2026 tahminleri.",
    "category": "Piyasa & Haberler"
  },
  {
    "text": "Airbnb için ev alırken yasal sınırlar nelerdir?",
    "category": "Piyasa & Haberler"
  },
  {
    "text": "Rezidans aidatları neden bu kadar yüksek?",
    "category": "Lüks & Prestij"
  },
  {
    "text": "Müstakil bir bahçeli ev için İstanbul'un en iyileri.",
    "category": "Tüyolar & Hatalar"
  },
  {
    "text": "Konut kredisi faizleri düştüğünde fiyatlar ne olur?",
    "category": "Piyasa & Haberler"
  },
  {
    "text": "Tapuda satış bedelini düşük göstermenin cezası nedir?",
    "category": "Tüyolar & Hatalar"
  },
  {
    "text": "Emlakçı komisyonu neden %2 + %2?",
    "category": "Tüyolar & Hatalar"
  },
  {
    "text": "İkinci el ev alırken tesisat kontrolü rehberi.",
    "category": "Tüyolar & Hatalar"
  },
  {
    "text": "Beylikdüzü'nün en lüks siteleri ve sundukları.",
    "category": "Beylikdüzü & Yerel"
  },
  {
    "text": "Yabancı yatırımcılar İstanbul'da nerelere bakıyor?",
    "category": "Yatırım & Kazanç"
  },
  {
    "text": "Emlak satışında video çekiminin gücü.",
    "category": "Tüyolar & Hatalar"
  },
  {
    "text": "Dron çekimi olmayan ilanlar neden geç satılıyor?",
    "category": "Lüks & Prestij"
  },
  {
    "text": "Evinizdeki mutfak dolaplarını boyayarak değer katın.",
    "category": "Hızlı & Pratik"
  },
  {
    "text": "Gayrimenkul yatırım ortaklıkları (GYO) mantıklı mı?",
    "category": "Yatırım & Kazanç"
  },
  {
    "text": "Kira artış oranlarında 2026 beklentileri.",
    "category": "Piyasa & Haberler"
  },
  {
    "text": "Acil nakit ihtiyacı için hızlı ev satma yöntemleri.",
    "category": "Hızlı & Pratik"
  },
  {
    "text": "Beylikdüzü'nde okul ve hastane yakınındaki projeler.",
    "category": "Beylikdüzü & Yerel"
  },
  {
    "text": "Emlak piyasasında kriz döneminde nasıl davranmalı?",
    "category": "Piyasa & Haberler"
  },
  {
    "text": "Tapu üzerindeki ipotek nasıl temizlenir?",
    "category": "Tüyolar & Hatalar"
  },
  {
    "text": "İnşaat aşamasında ev almanın avantaj ve dezavantajları.",
    "category": "Tüyolar & Hatalar"
  },
  {
    "text": "Müteahhit seçerken dikkat edilmesi gereken 5 kriter.",
    "category": "Tüyolar & Hatalar"
  },
  {
    "text": "Geleceğin parlayan yıldızı: Lojistik merkezleri ve emlak.",
    "category": "Tüyolar & Hatalar"
  },
  {
    "text": "Evinizin salonunda aydınlatma oyunları ile genişlik hissi.",
    "category": "Tüyolar & Hatalar"
  },
  {
    "text": "Bahçe katı daire alırken su yalıtımına dikkat!",
    "category": "Tüyolar & Hatalar"
  },
  {
    "text": "Beylikdüzü'nde sosyal yaşamın kalbi nerede atıyor?",
    "category": "Beylikdüzü & Yerel"
  },
  {
    "text": "Emlak ilanlarında fotoğraf çekme teknikleri.",
    "category": "Tüyolar & Hatalar"
  },
  {
    "text": "Sosyal medya üzerinden emlak pazarlama rehberi.",
    "category": "Tüyolar & Hatalar"
  },
  {
    "text": "Gayrimenkulde 'fırsat' ilanları nasıl yakalanır?",
    "category": "Tüyolar & Hatalar"
  },
  {
    "text": "Emlak danışmanı ile sözleşme yapmanın hukuki gücü.",
    "category": "Tüyolar & Hatalar"
  },
  {
    "text": "Tapu dairesinde imza atmadan önce son kontrol listesi.",
    "category": "Tüyolar & Hatalar"
  },
  {
    "text": "Evinizde koku yönetimi ile satış şansınızı artırın.",
    "category": "Tüyolar & Hatalar"
  },
  {
    "text": "Beylikdüzü Adnan Kahveci Mahallesi yatırım analizi.",
    "category": "Beylikdüzü & Yerel"
  },
  {
    "text": "Beylikdüzü Barış Mahallesi neden çok tercih ediliyor?",
    "category": "Beylikdüzü & Yerel"
  },
  {
    "text": "Yakuplu bölgesinde marina etkisinin fiyatlara yansıması.",
    "category": "Beylikdüzü & Yerel"
  },
  {
    "text": "Beylikdüzü'nde metrobüse yürüme mesafesinde en iyi siteler.",
    "category": "Beylikdüzü & Yerel"
  },
  {
    "text": "Emlak piyasasında 'kelepir' diye bir şey var mı?",
    "category": "Hızlı & Pratik"
  },
  {
    "text": "Gayrimenkul değerleme raporu neden önemlidir?",
    "category": "Piyasa & Haberler"
  },
  {
    "text": "Ekspertiz ücretini kim öder?",
    "category": "Tüyolar & Hatalar"
  },
  {
    "text": "Ev alırken belediye borçlarını kontrol ettiniz mi?",
    "category": "Tüyolar & Hatalar"
  },
  {
    "text": "Dükkan tapulu ev alınır mı? Riskler neler?",
    "category": "Tüyolar & Hatalar"
  },
  {
    "text": "Ofis katını konuta çevirmek mümkün mü?",
    "category": "Tüyolar & Hatalar"
  },
  {
    "text": "Güneş enerjili evlerin satış fiyatına etkisi.",
    "category": "Tüyolar & Hatalar"
  },
  {
    "text": "Akıllı ev sistemleri gerçekten gerekli mi?",
    "category": "Tüyolar & Hatalar"
  },
  {
    "text": "Evinizdeki balkonun kapalı olması değer artırır mı?",
    "category": "Tüyolar & Hatalar"
  },
  {
    "text": "Beylikdüzü'nde aileler için en uygun siteler.",
    "category": "Beylikdüzü & Yerel"
  },
  {
    "text": "Üniversite bölgelerinde öğrenciye kiralık ev yatırımı.",
    "category": "Yatırım & Kazanç"
  },
  {
    "text": "Yatırımlık tarlada 'toprak' cinsi neden önemli?",
    "category": "Yatırım & Kazanç"
  },
  {
    "text": "Zeytinlik şerhi olan arazilerde yapılaşma şartları.",
    "category": "Tüyolar & Hatalar"
  },
  {
    "text": "Emlak piyasasında 'sahibinden' yanılgısı.",
    "category": "Piyasa & Haberler"
  },
  {
    "text": "Gayrimenkul danışmanının gizli network'ü.",
    "category": "Tüyolar & Hatalar"
  },
  {
    "text": "RE/MAX Kaya ile Beylikdüzü'nde fark yaratan satışlar.",
    "category": "Beylikdüzü & Yerel"
  },
  {
    "text": "Evinizin girişini (antre) nasıl çekici kılarsınız?",
    "category": "Tüyolar & Hatalar"
  },
  {
    "text": "Emlak piyasasında mevsimsel dalgalanmalar.",
    "category": "Piyasa & Haberler"
  },
  {
    "text": "Kışın ev almak daha mı mantıklı?",
    "category": "Tüyolar & Hatalar"
  },
  {
    "text": "Yazlık bölgelerde kışın emlak fırsatları.",
    "category": "Tüyolar & Hatalar"
  },
  {
    "text": "Kıbrıs'ta sterlin bazlı kira geliri avantajı.",
    "category": "Tüyolar & Hatalar"
  },
  {
    "text": "Yurtdışından ev alırken vatandaşlık imkanları.",
    "category": "Tüyolar & Hatalar"
  },
  {
    "text": "Emlak vergisi muafiyetinden kimler yararlanabilir?",
    "category": "Piyasa & Haberler"
  },
  {
    "text": "Emekliler için emlak vergisinde büyük indirim.",
    "category": "Piyasa & Haberler"
  },
  {
    "text": "Evinizi kiraya verirken dikkat etmeniz gereken 10 madde.",
    "category": "Tüyolar & Hatalar"
  },
  {
    "text": "Tahliye taahhütnamesi geçerlilik şartları.",
    "category": "Tüyolar & Hatalar"
  },
  {
    "text": "Kiracı varken ev satışı nasıl yapılır?",
    "category": "Tüyolar & Hatalar"
  },
  {
    "text": "Beylikdüzü'nde yeni açılacak metro hattı durakları.",
    "category": "Beylikdüzü & Yerel"
  },
  {
    "text": "Beylikdüzü'nde değerini koruyan klasik projeler.",
    "category": "Beylikdüzü & Yerel"
  },
  {
    "text": "Emlak piyasasında doğru fiyatlandırma stratejisi.",
    "category": "Piyasa & Haberler"
  },
  {
    "text": "Evinizin manzarasının kapanma riskini nasıl anlarsınız?",
    "category": "Lüks & Prestij"
  },
  {
    "text": "Bitişik nizam binalarda yalıtım sorunları.",
    "category": "Tüyolar & Hatalar"
  },
  {
    "text": "Çatı katında akma ve rutubet nasıl önlenir?",
    "category": "Tüyolar & Hatalar"
  },
  {
    "text": "Emlak piyasasında 'balon' mu var? Gerçek veriler.",
    "category": "Piyasa & Haberler"
  },
  {
    "text": "Enflasyona karşı parayı korumanın yolu: Emlak.",
    "category": "Yatırım & Kazanç"
  },
  {
    "text": "Döviz bazında emlak fiyatları ne yöne gidiyor?",
    "category": "Yatırım & Kazanç"
  },
  {
    "text": "Beylikdüzü'nde ticari mülk yatırımı karlı mı?",
    "category": "Beylikdüzü & Yerel"
  },
  {
    "text": "Dükkan alırken tabela değeri analizi.",
    "category": "Tüyolar & Hatalar"
  },
  {
    "text": "Emlak piyasasında dijital dönüşüm: Online tapu.",
    "category": "Piyasa & Haberler"
  },
  {
    "text": "Webtapu üzerinden başvuru yapma rehberi.",
    "category": "Tüyolar & Hatalar"
  },
  {
    "text": "Emlak danışmanlığı profesyonel bir meslektir.",
    "category": "Tüyolar & Hatalar"
  },
  {
    "text": "Gayrimenkulde başarının anahtarı: Doğru analiz.",
    "category": "Tüyolar & Hatalar"
  },
  {
    "text": "Beylikdüzü Kavaklı bölgesi neden yükselişte?",
    "category": "Beylikdüzü & Yerel"
  },
  {
    "text": "Evinizdeki ışıklandırma satışı nasıl etkiler?",
    "category": "Tüyolar & Hatalar"
  },
  {
    "text": "Gayrimenkulde amortisman süresi nasıl hesaplanır?",
    "category": "Yatırım & Kazanç"
  },
  {
    "text": "Hisseli tapulu yerlerde şufa hakkı tehlikesi!",
    "category": "Tüyolar & Hatalar"
  },
  {
    "text": "Tapu takas sistemi ile güvenli alışveriş.",
    "category": "Tüyolar & Hatalar"
  },
  {
    "text": "Emlak piyasasında 2026'nın kazananları kim olacak?",
    "category": "Piyasa & Haberler"
  },
  {
    "text": "Kira sözleşmesinde tahliye taahhüdünün önemi.",
    "category": "Tüyolar & Hatalar"
  },
  {
    "text": "Beylikdüzü'nde spor imkanı en geniş siteler.",
    "category": "Beylikdüzü & Yerel"
  },
  {
    "text": "Ev alırken apartman yönetim planını istediniz mi?",
    "category": "Tüyolar & Hatalar"
  },
  {
    "text": "Gürültü kirliliği ev değerini ne kadar düşürür?",
    "category": "Tüyolar & Hatalar"
  },
  {
    "text": "Deprem sigortası (DASK) hakkında doğru bilinen yanlışlar.",
    "category": "Tüyolar & Hatalar"
  },
  {
    "text": "Evinizin mutfağını 10 bin TL altına yenileyin.",
    "category": "Tüyolar & Hatalar"
  },
  {
    "text": "Arsa mı, arazi mi? Hangisi daha karlı?",
    "category": "Yatırım & Kazanç"
  },
  {
    "text": "İmar barışından yararlanan evlerde son durum.",
    "category": "Tüyolar & Hatalar"
  },
  {
    "text": "Beylikdüzü'nde ulaşım projelerinin geleceği.",
    "category": "Beylikdüzü & Yerel"
  },
  {
    "text": "Emlak piyasasında 'duygusal fiyatlandırma' hatası.",
    "category": "Piyasa & Haberler"
  },
  {
    "text": "Evinizi ilk gören alıcıya satmanın püf noktaları.",
    "category": "Tüyolar & Hatalar"
  },
  {
    "text": "Emlak danışmanına en çok sorulan 10 soru.",
    "category": "Tüyolar & Hatalar"
  },
  {
    "text": "Rezidanslarda yaşam maliyeti ve gizli giderler.",
    "category": "Yatırım & Kazanç"
  },
  {
    "text": "Beylikdüzü'nde yeşil alanı en bol projeler.",
    "category": "Beylikdüzü & Yerel"
  },
  {
    "text": "Gayrimenkulde vergi planlaması nasıl yapılır?",
    "category": "Piyasa & Haberler"
  },
  {
    "text": "Satış sonrası tapu masrafları kimin sorumluluğunda?",
    "category": "Tüyolar & Hatalar"
  },
  {
    "text": "Ev alırken asansör bakımı neden önemlidir?",
    "category": "Tüyolar & Hatalar"
  },
  {
    "text": "Evinizdeki rutubet kokusundan kurtulma yolları.",
    "category": "Tüyolar & Hatalar"
  },
  {
    "text": "Emlak piyasasında 2026 bahar beklentileri.",
    "category": "Piyasa & Haberler"
  },
  {
    "text": "Daire alırken otopark hakkınızı kontrol edin.",
    "category": "Tüyolar & Hatalar"
  },
  {
    "text": "Beylikdüzü'nde çocuklu aileler için ideal bölgeler.",
    "category": "Beylikdüzü & Yerel"
  },
  {
    "text": "Emlak ilanlarında açıklama yazarken yapılan hatalar.",
    "category": "Tüyolar & Hatalar"
  },
  {
    "text": "Instagram Reels ile emlak satışı nasıl yapılır?",
    "category": "Tüyolar & Hatalar"
  },
  {
    "text": "Emlak videolarında hangi müzikler kullanılmalı?",
    "category": "Tüyolar & Hatalar"
  },
  {
    "text": "Ev gösterimi sırasında ev sahibinin yapmaması gerekenler.",
    "category": "Tüyolar & Hatalar"
  },
  {
    "text": "Emlak danışmanı seçerken referansın önemi.",
    "category": "Tüyolar & Hatalar"
  },
  {
    "text": "Beylikdüzü'nde kira çarpanı en düşük yerler.",
    "category": "Beylikdüzü & Yerel"
  },
  {
    "text": "Metropol yaşamından kaçış: Beylikdüzü'nün sakinleri.",
    "category": "Beylikdüzü & Yerel"
  },
  {
    "text": "Yatırımlık mülkte konum mu, bina yaşı mı?",
    "category": "Yatırım & Kazanç"
  },
  {
    "text": "Eski binalarda kentsel dönüşüm süreci nasıl başlar?",
    "category": "Tüyolar & Hatalar"
  },
  {
    "text": "Müteahhitten ev alırken teminat sorma hakkınız.",
    "category": "Tüyolar & Hatalar"
  },
  {
    "text": "Emlak piyasasında 'fiyatı şişirilmiş' ilanları ayıklama.",
    "category": "Piyasa & Haberler"
  },
  {
    "text": "Tapuda satış bedeli ile kredi tutarı uyumu.",
    "category": "Piyasa & Haberler"
  },
  {
    "text": "Emlak vergisi ödemelerinde son gün uyarısı.",
    "category": "Piyasa & Haberler"
  },
  {
    "text": "Beylikdüzü'nde en iyi manzaralı teras katları.",
    "category": "Beylikdüzü & Yerel"
  },
  {
    "text": "Evinizdeki kapı kollarını değiştirerek modern hava katın.",
    "category": "Hızlı & Pratik"
  },
  {
    "text": "Gayrimenkulde doğru zamanı beklemenin maliyeti.",
    "category": "Yatırım & Kazanç"
  },
  {
    "text": "Piyasa durgunken ev satmanın stratejileri.",
    "category": "Piyasa & Haberler"
  },
  {
    "text": "Emlak danışmanlığında teknolojinin kullanımı.",
    "category": "Tüyolar & Hatalar"
  },
  {
    "text": "Sanal tur (3D Tour) ile ev gezmenin avantajları.",
    "category": "Lüks & Prestij"
  },
  {
    "text": "Evinizin bahçesini düzenleyerek %10 değer katın.",
    "category": "Tüyolar & Hatalar"
  },
  {
    "text": "Beylikdüzü'nde alışveriş merkezlerine yakın projeler.",
    "category": "Beylikdüzü & Yerel"
  },
  {
    "text": "Emlak piyasasında emlakçıların paylaştığı sırlar.",
    "category": "Piyasa & Haberler"
  },
  {
    "text": "Tapu dairesindeki randevu süreci nasıl işler?",
    "category": "Tüyolar & Hatalar"
  },
  {
    "text": "Ev alırken yanınızda mutlaka uzman götürün.",
    "category": "Tüyolar & Hatalar"
  },
  {
    "text": "Evinizin pencerelerindeki ısı yalıtımı kontrolü.",
    "category": "Tüyolar & Hatalar"
  },
  {
    "text": "Gayrimenkul yatırımında bölgesel odaklanma.",
    "category": "Yatırım & Kazanç"
  },
  {
    "text": "Beylikdüzü'nün en eski ve en yeni binaları.",
    "category": "Beylikdüzü & Yerel"
  },
  {
    "text": "Emlak piyasasında 2026 yaz tahminleri.",
    "category": "Piyasa & Haberler"
  },
  {
    "text": "Kira artışında yasal sınırın üzerine çıkılabilir mi?",
    "category": "Piyasa & Haberler"
  },
  {
    "text": "Evinizi eşyalı mı, eşyasız mı satmalısınız?",
    "category": "Tüyolar & Hatalar"
  },
  {
    "text": "Beylikdüzü'nde yaşam kalitesini artıran faktörler.",
    "category": "Beylikdüzü & Yerel"
  },
  {
    "text": "Gayrimenkulde sürdürülebilirlik ve yeşil binalar.",
    "category": "Tüyolar & Hatalar"
  },
  {
    "text": "Evinizdeki banyo fayanslarını boyama rehberi.",
    "category": "Hızlı & Pratik"
  },
  {
    "text": "Beylikdüzü'nde ulaşımı en kolay ofis alanları.",
    "category": "Beylikdüzü & Yerel"
  },
  {
    "text": "Emlak piyasasında fırsatları kaçırmama rehberi.",
    "category": "Piyasa & Haberler"
  },
  {
    "text": "Tapu işlemlerinde vekaletname ile satışın riskleri.",
    "category": "Tüyolar & Hatalar"
  },
  {
    "text": "Ev alırken bina kimlik sertifikasına bakın.",
    "category": "Tüyolar & Hatalar"
  },
  {
    "text": "Evinizin boyasını yenilemek satış süresini kısaltır mı?",
    "category": "Hızlı & Pratik"
  },
  {
    "text": "Gayrimenkul yatırımında risk yönetimi.",
    "category": "Yatırım & Kazanç"
  },
  {
    "text": "Beylikdüzü'nde akşam yürüyüşü yapılacak en iyi parklar.",
    "category": "Beylikdüzü & Yerel"
  },
  {
    "text": "Emlak piyasasında 'sıcak' alıcıları tanıma.",
    "category": "Piyasa & Haberler"
  },
  {
    "text": "Tapu harcı indirimleri ne zaman gelir?",
    "category": "Piyasa & Haberler"
  },
  {
    "text": "Ev alırken komşuların önemi ve araştırma yöntemleri.",
    "category": "Tüyolar & Hatalar"
  },
  {
    "text": "Evinizdeki depolama alanlarını artırma taktikleri.",
    "category": "Tüyolar & Hatalar"
  },
  {
    "text": "Gayrimenkulde kaldıraçlı işlem (Kredi kullanımı).",
    "category": "Piyasa & Haberler"
  },
  {
    "text": "Beylikdüzü'nde prestijli yaşamın adresi: Beykasaba.",
    "category": "Beylikdüzü & Yerel"
  },
  {
    "text": "Emlak piyasasında 2026 kış vizyonu.",
    "category": "Piyasa & Haberler"
  },
  {
    "text": "Kira gelir vergisi beyannamesi nasıl verilir?",
    "category": "Piyasa & Haberler"
  },
  {
    "text": "Evinizi satarken neden bir profesyonele güvenmelisiniz?",
    "category": "Tüyolar & Hatalar"
  },
  {
    "text": "Beylikdüzü'nde en iyi kreşlere yakın siteler.",
    "category": "Beylikdüzü & Yerel"
  },
  {
    "text": "Gayrimenkulde portföy çeşitlendirmesi.",
    "category": "Tüyolar & Hatalar"
  },
  {
    "text": "Evinizdeki parkelerin bakımını yaparak parlatın.",
    "category": "Yatırım & Kazanç"
  },
  {
    "text": "Beylikdüzü'nde marina hayatı ve avantajları.",
    "category": "Beylikdüzü & Yerel"
  },
  {
    "text": "Emlak piyasasında doğru danışmanla çalışmanın karlılığı.",
    "category": "Yatırım & Kazanç"
  },
  {
    "text": "Tapuda satış işlemi sonrası yapılması gerekenler.",
    "category": "Tüyolar & Hatalar"
  },
  {
    "text": "Ev alırken su deposu ve jeneratör kontrolü.",
    "category": "Tüyolar & Hatalar"
  },
  {
    "text": "Evinizdeki tavan yüksekliğinin fiyata etkisi.",
    "category": "Tüyolar & Hatalar"
  },
  {
    "text": "Gayrimenkulde uzun vadeli yatırımın gücü.",
    "category": "Yatırım & Kazanç"
  },
  {
    "text": "Beylikdüzü'nde genç profesyoneller için küçük daireler.",
    "category": "Beylikdüzü & Yerel"
  },
  {
    "text": "Emlak piyasasında 'bekle-gör' politikasının riskleri.",
    "category": "Piyasa & Haberler"
  },
  {
    "text": "Kira öder gibi ev sahibi olmanın yolları.",
    "category": "Tüyolar & Hatalar"
  },
  {
    "text": "Evinizi satmadan önce profesyonel temizlik yaptırın.",
    "category": "Hızlı & Pratik"
  },
  {
    "text": "Beylikdüzü'nde değer artışı en yüksek mahalleler.",
    "category": "Beylikdüzü & Yerel"
  },
  {
    "text": "Gayrimenkulde yasal mevzuat değişiklikleri.",
    "category": "Piyasa & Haberler"
  },
  {
    "text": "Emlak piyasasında 2027 projeksiyonu.",
    "category": "Piyasa & Haberler"
  },
  {
    "text": "Tapu dairesinde yaşanabilecek aksaklıklara hazırlık.",
    "category": "Tüyolar & Hatalar"
  },
  {
    "text": "Ev alırken ısı pay ölçer sisteminin avantajı.",
    "category": "Tüyolar & Hatalar"
  },
  {
    "text": "Evinizdeki petek temizliğinin yakıt faturasına etkisi.",
    "category": "Tüyolar & Hatalar"
  },
  {
    "text": "Gayrimenkul yatırımında dikkat edilmesi gereken 3 kural.",
    "category": "Yatırım & Kazanç"
  },
  {
    "text": "Beylikdüzü'nde modern mimari ile öne çıkan binalar.",
    "category": "Beylikdüzü & Yerel"
  },
  {
    "text": "Emlak piyasasında RE/MAX kalitesi.",
    "category": "Piyasa & Haberler"
  },
  {
    "text": "Evinizi satarken doğru fotoğraf açısını yakalayın.",
    "category": "Tüyolar & Hatalar"
  },
  {
    "text": "Gayrimenkulde kazancın ilk adımı: Alırken kazanmak.",
    "category": "Tüyolar & Hatalar"
  },
  {
    "text": "Beylikdüzü'nde kiracısı hazır satılık daireler.",
    "category": "Beylikdüzü & Yerel"
  },
  {
    "text": "Emlak piyasasında 'fiyatı düşenler' listesi.",
    "category": "Piyasa & Haberler"
  },
  {
    "text": "Tapu harcı ödemesinde kredi kartı dönemi.",
    "category": "Piyasa & Haberler"
  },
  {
    "text": "Ev alırken doğalgaz projesini kontrol edin.",
    "category": "Tüyolar & Hatalar"
  },
  {
    "text": "Beylikdüzü'nde spor salonu en donanımlı siteler.",
    "category": "Beylikdüzü & Yerel"
  },
  {
    "text": "Gayrimenkulde amortisman süresi 15 yılın altında mı?",
    "category": "Yatırım & Kazanç"
  },
  {
    "text": "Hisseli arsada ortaklığın giderilmesi davası.",
    "category": "Tüyolar & Hatalar"
  },
  {
    "text": "Emlak danışmanı ile çalışmanın 7 altın kuralı.",
    "category": "Tüyolar & Hatalar"
  },
  {
    "text": "Evinizdeki mutfak tezgahını yenileme fikirleri.",
    "category": "Hızlı & Pratik"
  },
  {
    "text": "Beylikdüzü'nde çocuk oyun alanı en büyük siteler.",
    "category": "Beylikdüzü & Yerel"
  },
  {
    "text": "Gayrimenkul yatırımında lokasyon mu, kalite mi?",
    "category": "Yatırım & Kazanç"
  },
  {
    "text": "Tapu devrinde blokeli çek kullanımının güvenliği.",
    "category": "Tüyolar & Hatalar"
  },
  {
    "text": "Ev alırken binanın statik raporunu istediniz mi?",
    "category": "Piyasa & Haberler"
  },
  {
    "text": "Evinizdeki eski mobilyaları boyayarak değer katın.",
    "category": "Hızlı & Pratik"
  },
  {
    "text": "Beylikdüzü'nde metrobüse en yakın 5 kiralık daire.",
    "category": "Beylikdüzü & Yerel"
  },
  {
    "text": "Emlak piyasasında 2026'nın parlayan yıldızları.",
    "category": "Piyasa & Haberler"
  },
  {
    "text": "Kira artış oranlarında yüzde 25 sınırı kalkınca ne oldu?",
    "category": "Tüyolar & Hatalar"
  },
  {
    "text": "Evinizi hızlı satmak için 'sahneleme' (Staging) yapın.",
    "category": "Hızlı & Pratik"
  },
  {
    "text": "Beylikdüzü'nde deniz manzaralı en uygun fiyatlı yerler.",
    "category": "Beylikdüzü & Yerel"
  },
  {
    "text": "Gayrimenkul yatırım sepetinde arsanın payı ne olmalı?",
    "category": "Yatırım & Kazanç"
  },
  {
    "text": "Tapu dairesinde yaşlılar için sağlık raporu şartı.",
    "category": "Piyasa & Haberler"
  },
  {
    "text": "Ev alırken emlakçı hizmet bedeli pazarlığı yapılır mı?",
    "category": "Tüyolar & Hatalar"
  },
  {
    "text": "Evinizdeki antreyi (giriş) daha geniş gösterme yolları.",
    "category": "Tüyolar & Hatalar"
  },
  {
    "text": "Beylikdüzü Gürpınar bölgesinde müstakil yaşam.",
    "category": "Beylikdüzü & Yerel"
  },
  {
    "text": "Gayrimenkulde doğru yatırımın 5 temel prensibi.",
    "category": "Yatırım & Kazanç"
  },
  {
    "text": "Emlak piyasasında 'aciliyet' psikolojisi ile satış.",
    "category": "Hızlı & Pratik"
  },
  {
    "text": "Kira geliri elde ederken vergi avantajları.",
    "category": "Piyasa & Haberler"
  },
  {
    "text": "Evinizi satmadan önce boyatmanın geri dönüşü.",
    "category": "Hızlı & Pratik"
  },
  {
    "text": "Beylikdüzü'nde site aidatlarının en uygun olduğu yerler.",
    "category": "Beylikdüzü & Yerel"
  },
  {
    "text": "Gayrimenkul danışmanlığında profesyonel etik kurallar.",
    "category": "Tüyolar & Hatalar"
  },
  {
    "text": "Tapuda intikal işlemleri nasıl yapılır?",
    "category": "Tüyolar & Hatalar"
  },
  {
    "text": "Ev alırken şebeke suyunun kalitesini kontrol edin.",
    "category": "Tüyolar & Hatalar"
  },
  {
    "text": "Evinizdeki balkon dekorasyonu ile satış şansınızı artırın.",
    "category": "Tüyolar & Hatalar"
  },
  {
    "text": "Beylikdüzü'nde yatırım için en mantıklı mahalleler.",
    "category": "Beylikdüzü & Yerel"
  },
  {
    "text": "Gayrimenkulde enflasyona karşı koruma kalkanı.",
    "category": "Yatırım & Kazanç"
  },
  {
    "text": "Emlak piyasasında 'doğru fiyat' tespiti nasıl yapılır?",
    "category": "Piyasa & Haberler"
  },
  {
    "text": "Tapuda satış bedelini düşük göstermenin riskleri.",
    "category": "Tüyolar & Hatalar"
  },
  {
    "text": "Ev alırken bodrum kattaki rutubeti nasıl anlarsınız?",
    "category": "Tüyolar & Hatalar"
  },
  {
    "text": "Evinizdeki dolap kapaklarını değiştirerek modernleşin.",
    "category": "Hızlı & Pratik"
  },
  {
    "text": "Beylikdüzü'nde sağlık merkezlerine yakın projeler.",
    "category": "Beylikdüzü & Yerel"
  },
  {
    "text": "Gayrimenkul yatırımında 'erken kalkan yol alır'.",
    "category": "Yatırım & Kazanç"
  },
  {
    "text": "Emlak piyasasında kış sezonunda daire bakmanın avantajları.",
    "category": "Piyasa & Haberler"
  },
  {
    "text": "Tapu takyidat belgesi nedir, neden alınmalıdır?",
    "category": "Tüyolar & Hatalar"
  },
  {
    "text": "Ev alırken yangın merdiveni ve güvenlik önlemleri.",
    "category": "Tüyolar & Hatalar"
  },
  {
    "text": "Evinizdeki ışık anahtarlarını yenileyerek detaylara önem verin.",
    "category": "Tüyolar & Hatalar"
  },
  {
    "text": "Beylikdüzü'nde sosyal tesisleri en zengin projeler.",
    "category": "Beylikdüzü & Yerel"
  },
  {
    "text": "Gayrimenkulde kira garantili sistemler nasıl işler?",
    "category": "Tüyolar & Hatalar"
  },
  {
    "text": "Emlak danışmanı neden tek yetki ister?",
    "category": "Tüyolar & Hatalar"
  },
  {
    "text": "Tapu işlemlerinde e-devlet üzerinden başvuru kolaylığı.",
    "category": "Tüyolar & Hatalar"
  },
  {
    "text": "Ev alırken çatı izolasyonunun önemini hafife almayın.",
    "category": "Tüyolar & Hatalar"
  },
  {
    "text": "Evinizdeki perdelere yeni bir soluk getirin.",
    "category": "Yatırım & Kazanç"
  },
  {
    "text": "Beylikdüzü'nde en iyi manzaralı restoranlara yakın siteler.",
    "category": "Beylikdüzü & Yerel"
  },
  {
    "text": "Gayrimenkul yatırımında kentsel dönüşüm fırsatları.",
    "category": "Yatırım & Kazanç"
  },
  {
    "text": "Emlak piyasasında doğru zamanı belirleyen faktörler.",
    "category": "Piyasa & Haberler"
  },
  {
    "text": "Tapu dairesinde harç ödemesi nasıl yapılır?",
    "category": "Tüyolar & Hatalar"
  },
  {
    "text": "Ev alırken mutfak dolaplarının menteşelerini kontrol edin.",
    "category": "Tüyolar & Hatalar"
  },
  {
    "text": "Evinizdeki parkelerin rengini değiştirerek ferahlık yakalayın.",
    "category": "Hızlı & Pratik"
  },
  {
    "text": "Beylikdüzü'nde ulaşım ağlarına en entegre projeler.",
    "category": "Beylikdüzü & Yerel"
  },
  {
    "text": "Gayrimenkulde amortisman süresini kısaltmanın yolları.",
    "category": "Yatırım & Kazanç"
  },
  {
    "text": "Emlak danışmanlığında RE/MAX Kaya farkı.",
    "category": "Tüyolar & Hatalar"
  },
  {
    "text": "Tapu işlemlerinde sahteciliğe karşı SMS kilidi.",
    "category": "Tüyolar & Hatalar"
  },
  {
    "text": "Ev alırken elektrik tesisatının gücünü kontrol edin.",
    "category": "Tüyolar & Hatalar"
  },
  {
    "text": "Evinizdeki kapıları boyayarak yenilikçi bir hava katın.",
    "category": "Hızlı & Pratik"
  },
  {
    "text": "Beylikdüzü'nde yatırım yapılacak ticari dükkanlar.",
    "category": "Beylikdüzü & Yerel"
  },
  {
    "text": "Gayrimenkul yatırımında bölgesel piyasa analizi.",
    "category": "Yatırım & Kazanç"
  },
  {
    "text": "Emlak piyasasında doğru danışman seçimi neden kritiktir?",
    "category": "Piyasa & Haberler"
  },
  {
    "text": "Tapu senedindeki şerh ve beyanların anlamı.",
    "category": "Tüyolar & Hatalar"
  },
  {
    "text": "Ev alırken apartman boşluğundaki havalandırmayı kontrol edin.",
    "category": "Tüyolar & Hatalar"
  },
  {
    "text": "Evinizdeki banyo aynasını büyüterek genişlik hissi yaratın.",
    "category": "Tüyolar & Hatalar"
  },
  {
    "text": "Beylikdüzü'nde en huzurlu ve sessiz siteler.",
    "category": "Beylikdüzü & Yerel"
  },
  {
    "text": "Gayrimenkulde kira getirisi yüksek bölgeler.",
    "category": "Yatırım & Kazanç"
  },
  {
    "text": "Emlak piyasasında satış kapama teknikleri.",
    "category": "Piyasa & Haberler"
  },
  {
    "text": "Tapuda satış işlemi ne kadar sürer?",
    "category": "Tüyolar & Hatalar"
  },
  {
    "text": "Ev alırken pencerelerin markası ve kalitesi neden önemli?",
    "category": "Tüyolar & Hatalar"
  },
  {
    "text": "Evinizdeki radyatörleri boyayarak şıklık katın.",
    "category": "Hızlı & Pratik"
  },
  {
    "text": "Beylikdüzü'nde en modern iç mimariye sahip daireler.",
    "category": "Beylikdüzü & Yerel"
  },
  {
    "text": "Gayrimenkul yatırımında gelecek vadeden semtler.",
    "category": "Yatırım & Kazanç"
  },
  {
    "text": "Emlak piyasasında müşteri memnuniyeti odağı.",
    "category": "Piyasa & Haberler"
  },
  {
    "text": "Tapu işlemlerinde randevu almadan gitmeyin.",
    "category": "Tüyolar & Hatalar"
  },
  {
    "text": "Ev alırken banyo giderlerinin akışını kontrol edin.",
    "category": "Tüyolar & Hatalar"
  },
  {
    "text": "Evinizdeki zemin döşemelerini yenilemenin maliyeti.",
    "category": "Yatırım & Kazanç"
  },
  {
    "text": "Beylikdüzü'nde en geniş peyzaj alanına sahip projeler.",
    "category": "Beylikdüzü & Yerel"
  },
  {
    "text": "Gayrimenkul yatırımında sabrın önemi.",
    "category": "Yatırım & Kazanç"
  },
  {
    "text": "Emlak piyasasında RE/MAX kalitesi ile güvenli satış.",
    "category": "Piyasa & Haberler"
  },
  {
    "text": "Tapu devrinde kimlik doğrulama sistemleri.",
    "category": "Tüyolar & Hatalar"
  },
  {
    "text": "Ev alırken binanın giriş kapısının güvenliği.",
    "category": "Tüyolar & Hatalar"
  },
  {
    "text": "Evinizdeki asma tavan ve ışıklandırma detayları.",
    "category": "Tüyolar & Hatalar"
  },
  {
    "text": "Beylikdüzü'nde yatırım potansiyeli yüksek rezidanslar.",
    "category": "Beylikdüzü & Yerel"
  },
  {
    "text": "Gayrimenkulde portföy yönetimi ve danışmanlık.",
    "category": "Tüyolar & Hatalar"
  },
  {
    "text": "Emlak piyasasında 2026 son çeyrek beklentileri.",
    "category": "Piyasa & Haberler"
  },
  {
    "text": "Tapuda satış bedeli ödemesinde güvenli yöntemler.",
    "category": "Tüyolar & Hatalar"
  },
  {
    "text": "Ev alırken merdivenlerin genişliği ve konforu.",
    "category": "Tüyolar & Hatalar"
  },
  {
    "text": "Evinizdeki prizleri ve anahtarları modern tasarımlarla değiştirin.",
    "category": "Hızlı & Pratik"
  },
  {
    "text": "Beylikdüzü'nde denize en yakın 3 mahalle.",
    "category": "Beylikdüzü & Yerel"
  },
  {
    "text": "Gayrimenkul yatırımında kira artış potansiyeli.",
    "category": "Yatırım & Kazanç"
  },
  {
    "text": "Emlak piyasasında doğru fiyatlandırmanın kazandırdıkları.",
    "category": "Piyasa & Haberler"
  },
  {
    "text": "Tapuda satış işlemi öncesi hazırlık listesi.",
    "category": "Tüyolar & Hatalar"
  },
  {
    "text": "Ev alırken balkonun rüzgar yönünü kontrol edin.",
    "category": "Tüyolar & Hatalar"
  },
  {
    "text": "Evinizdeki peteklerin bakımını yaparak kışa hazırlanın.",
    "category": "Yatırım & Kazanç"
  },
  {
    "text": "Gayrimenkulde başarının adresi: RE/MAX Kaya.",
    "category": "Tüyolar & Hatalar"
  },
  {
    "text": "Beylikdüzü'nde acil satılık kelepir daireler.",
    "category": "Beylikdüzü & Yerel"
  },
  {
    "text": "Emlak piyasasında 2026'nın en büyük fırsatı.",
    "category": "Piyasa & Haberler"
  },
  {
    "text": "Tapu harcı hesaplama motoru nasıl kullanılır?",
    "category": "Piyasa & Haberler"
  },
  {
    "text": "Ev alırken asansörün markasına neden bakmalısınız?",
    "category": "Tüyolar & Hatalar"
  },
  {
    "text": "Beylikdüzü'nde spor alanları en geniş site.",
    "category": "Beylikdüzü & Yerel"
  },
  {
    "text": "Gayrimenkulde amortisman süresi ve kira çarpanı.",
    "category": "Yatırım & Kazanç"
  },
  {
    "text": "Hisseli tapu alırken yapılan en büyük hata.",
    "category": "Tüyolar & Hatalar"
  },
  {
    "text": "Emlak danışmanı ile satış sürecini hızlandırın.",
    "category": "Tüyolar & Hatalar"
  },
  {
    "text": "Evinizdeki mutfak dolaplarını boyayarak yenileyin.",
    "category": "Hızlı & Pratik"
  },
  {
    "text": "Beylikdüzü'nde çocuk dostu en iyi 5 site.",
    "category": "Beylikdüzü & Yerel"
  },
  {
    "text": "Gayrimenkul yatırımında bölge analizi nasıl yapılır?",
    "category": "Yatırım & Kazanç"
  },
  {
    "text": "Tapu devrinde bloke çek sisteminin avantajları.",
    "category": "Tüyolar & Hatalar"
  },
  {
    "text": "Ev alırken binanın deprem raporunu inceleyin.",
    "category": "Piyasa & Haberler"
  },
  {
    "text": "Evinizdeki eski kapıları modern boyalarla yenileyin.",
    "category": "Hızlı & Pratik"
  },
  {
    "text": "Beylikdüzü'nde metrobüse 2 dakika mesafeli evler.",
    "category": "Beylikdüzü & Yerel"
  },
  {
    "text": "Emlak piyasasında gelecek yılın trendleri.",
    "category": "Piyasa & Haberler"
  },
  {
    "text": "Kira artış oranlarında yasal haklarınızı bilin.",
    "category": "Piyasa & Haberler"
  },
  {
    "text": "Evinizi satarken doğru fiyat belirlemenin önemi.",
    "category": "Tüyolar & Hatalar"
  },
  {
    "text": "Beylikdüzü'nde deniz manzaralı lüks daireler.",
    "category": "Beylikdüzü & Yerel"
  },
  {
    "text": "Gayrimenkul yatırımında arsanın uzun vadeli gücü.",
    "category": "Yatırım & Kazanç"
  },
  {
    "text": "Tapu dairesinde işlemler kaç saat sürer?",
    "category": "Tüyolar & Hatalar"
  },
  {
    "text": "Ev alırken emlakçınıza sormanız gereken kritik sorular.",
    "category": "Tüyolar & Hatalar"
  },
  {
    "text": "Evinizdeki antreyi ayna ile daha geniş gösterin.",
    "category": "Tüyolar & Hatalar"
  },
  {
    "text": "Beylikdüzü'nün en sakin ve huzurlu mahallesi.",
    "category": "Beylikdüzü & Yerel"
  },
  {
    "text": "Gayrimenkulde doğru yatırımın 3 altın kuralı.",
    "category": "Yatırım & Kazanç"
  },
  {
    "text": "Emlak piyasasında psikolojik fiyatlama teknikleri.",
    "category": "Piyasa & Haberler"
  },
  {
    "text": "Kira gelirini artırmanın en kolay yolları.",
    "category": "Tüyolar & Hatalar"
  },
  {
    "text": "Evinizi satmadan önce yapmanız gereken temizlik.",
    "category": "Hızlı & Pratik"
  },
  {
    "text": "Beylikdüzü'nde en düşük aidatlı siteler.",
    "category": "Beylikdüzü & Yerel"
  },
  {
    "text": "Gayrimenkul danışmanlığında global standartlar.",
    "category": "Tüyolar & Hatalar"
  },
  {
    "text": "Tapuda intikal ve veraset işlemleri rehberi.",
    "category": "Tüyolar & Hatalar"
  },
  {
    "text": "Ev alırken su tesisatını mutlaka kontrol edin.",
    "category": "Tüyolar & Hatalar"
  },
  {
    "text": "Evinizdeki balkon dekorasyonu ile fark yaratın.",
    "category": "Tüyolar & Hatalar"
  },
  {
    "text": "Beylikdüzü'nde yatırımın kalbi hangi mahalle?",
    "category": "Beylikdüzü & Yerel"
  },
  {
    "text": "Gayrimenkulde enflasyon koruması nasıl sağlanır?",
    "category": "Yatırım & Kazanç"
  },
  {
    "text": "Emlak piyasasında gerçek fırsatları yakalama.",
    "category": "Piyasa & Haberler"
  },
  {
    "text": "Tapuda satış bedelini gizlemenin yasal cezaları.",
    "category": "Piyasa & Haberler"
  },
  {
    "text": "Ev alırken bodrum katın avantaj ve dezavantajları.",
    "category": "Tüyolar & Hatalar"
  },
  {
    "text": "Evinizdeki mobilyaları boyayarak dekorasyonu değiştirin.",
    "category": "Hızlı & Pratik"
  },
  {
    "text": "Beylikdüzü'nde yeni yapılan hastaneye yakın evler.",
    "category": "Beylikdüzü & Yerel"
  },
  {
    "text": "Gayrimenkul yatırımında zamanlama her şeydir.",
    "category": "Yatırım & Kazanç"
  },
  {
    "text": "Emlak piyasasında kışın ev almanın karları.",
    "category": "Piyasa & Haberler"
  },
  {
    "text": "Tapu takyidat belgesinde nelere dikkat edilmeli?",
    "category": "Tüyolar & Hatalar"
  },
  {
    "text": "Ev alırken bina güvenliği ve kamera sistemleri.",
    "category": "Tüyolar & Hatalar"
  },
  {
    "text": "Evinizdeki aydınlatma ile atmosferi değiştirin.",
    "category": "Hızlı & Pratik"
  },
  {
    "text": "Beylikdüzü'nde en iyi peyzaja sahip 3 proje.",
    "category": "Beylikdüzü & Yerel"
  },
  {
    "text": "Gayrimenkulde kira garantisi veren firmalar.",
    "category": "Tüyolar & Hatalar"
  },
  {
    "text": "Emlak danışmanı ile çalışmanın 5 temel faydası.",
    "category": "Tüyolar & Hatalar"
  },
  {
    "text": "Tapu işlemlerinde e-devlet başvuru rehberi.",
    "category": "Tüyolar & Hatalar"
  },
  {
    "text": "Ev alırken çatı izolasyonunu kontrol ettiniz mi?",
    "category": "Tüyolar & Hatalar"
  },
  {
    "text": "Evinizdeki eski eşyaları dönüştürerek değer katın.",
    "category": "Tüyolar & Hatalar"
  },
  {
    "text": "Beylikdüzü'nde marina ve sahil şeridi fırsatları.",
    "category": "Beylikdüzü & Yerel"
  },
  {
    "text": "Gayrimenkul yatırımında kentsel dönüşüm süreci.",
    "category": "Yatırım & Kazanç"
  },
  {
    "text": "Emlak piyasasında doğru analiz ile kazanmak.",
    "category": "Piyasa & Haberler"
  },
  {
    "text": "Tapuda harç ödemesi yaparken dikkat edilecekler.",
    "category": "Tüyolar & Hatalar"
  },
  {
    "text": "Ev alırken mutfak dolabı kalitesinin önemi.",
    "category": "Tüyolar & Hatalar"
  },
  {
    "text": "Evinizdeki zemin döşemesini yenilemenin yolları.",
    "category": "Hızlı & Pratik"
  },
  {
    "text": "Beylikdüzü'nde ulaşım projelerinin bölgeye etkisi.",
    "category": "Beylikdüzü & Yerel"
  },
  {
    "text": "Gayrimenkulde amortisman süresini hesaplayın.",
    "category": "Yatırım & Kazanç"
  },
  {
    "text": "Emlak danışmanlığında profesyonel yaklaşım.",
    "category": "Tüyolar & Hatalar"
  },
  {
    "text": "Tapu güvenliği için SMS onay sistemi.",
    "category": "Tüyolar & Hatalar"
  },
  {
    "text": "Ev alırken elektrik panosu ve sigortaları kontrol edin.",
    "category": "Tüyolar & Hatalar"
  },
  {
    "text": "Evinizdeki iç kapıları boyayarak şıklık katın.",
    "category": "Hızlı & Pratik"
  },
  {
    "text": "Beylikdüzü'nde ticari yatırımın püf noktaları.",
    "category": "Beylikdüzü & Yerel"
  },
  {
    "text": "Gayrimenkul yatırımında pazar araştırması.",
    "category": "Yatırım & Kazanç"
  },
  {
    "text": "Emlak piyasasında danışman desteğinin önemi.",
    "category": "Piyasa & Haberler"
  },
  {
    "text": "Tapu senedi üzerindeki bilgiler ne anlatıyor?",
    "category": "Tüyolar & Hatalar"
  },
  {
    "text": "Ev alırken apartman aydınlık boşluğunu kontrol edin.",
    "category": "Tüyolar & Hatalar"
  },
  {
    "text": "Evinizdeki banyo aynası ile ferahlık sağlayın.",
    "category": "Tüyolar & Hatalar"
  },
  {
    "text": "Beylikdüzü'nün en huzurlu site yaşamları.",
    "category": "Beylikdüzü & Yerel"
  },
  {
    "text": "Gayrimenkulde kira getirisi en yüksek semtler.",
    "category": "Yatırım & Kazanç"
  },
  {
    "text": "Emlak piyasasında hızlı satış teknikleri.",
    "category": "Hızlı & Pratik"
  },
  {
    "text": "Tapuda satış işlemi kaç gün sürer?",
    "category": "Tüyolar & Hatalar"
  },
  {
    "text": "Ev alırken cam ve pencere yalıtımına bakın.",
    "category": "Tüyolar & Hatalar"
  },
  {
    "text": "Evinizdeki radyatörleri modern tasarımlarla boyayın.",
    "category": "Hızlı & Pratik"
  },
  {
    "text": "Beylikdüzü'nde en şık iç tasarımlı daireler.",
    "category": "Beylikdüzü & Yerel"
  },
  {
    "text": "Gayrimenkul yatırımında yükselen bölgeler.",
    "category": "Yatırım & Kazanç"
  },
  {
    "text": "Emlak piyasasında müşteri ilişkileri yönetimi.",
    "category": "Piyasa & Haberler"
  },
  {
    "text": "Tapuda randevu alma ve takip süreci.",
    "category": "Tüyolar & Hatalar"
  },
  {
    "text": "Ev alırken gider tesisatını test edin.",
    "category": "Tüyolar & Hatalar"
  },
  {
    "text": "Evinizdeki yer karolarını boyama rehberi.",
    "category": "Hızlı & Pratik"
  },
  {
    "text": "Beylikdüzü'nde en büyük yeşil alana sahip site.",
    "category": "Beylikdüzü & Yerel"
  },
  {
    "text": "Gayrimenkul yatırımında sabırlı olmanın kazancı.",
    "category": "Yatırım & Kazanç"
  },
  {
    "text": "Emlak piyasasında güvenin adresi: RE/MAX.",
    "category": "Piyasa & Haberler"
  },
  {
    "text": "Tapu devrinde biyometrik doğrulama sistemleri.",
    "category": "Tüyolar & Hatalar"
  },
  {
    "text": "Ev alırken bina girişinin bakımı ve temizliği.",
    "category": "Tüyolar & Hatalar"
  },
  {
    "text": "Evinizdeki tavan ve ışık havuzu detayları.",
    "category": "Lüks & Prestij"
  },
  {
    "text": "Beylikdüzü'nde prim yapacak rezidans daireler.",
    "category": "Beylikdüzü & Yerel"
  },
  {
    "text": "Gayrimenkul portföyü nasıl oluşturulur?",
    "category": "Tüyolar & Hatalar"
  },
  {
    "text": "Emlak piyasasında 2026 sonu öngörüleri.",
    "category": "Piyasa & Haberler"
  },
  {
    "text": "Tapuda güvenli ödeme yöntemleri nelerdir?",
    "category": "Tüyolar & Hatalar"
  },
  {
    "text": "Ev alırken merdiven boşluğu ve asansör konforu.",
    "category": "Tüyolar & Hatalar"
  },
  {
    "text": "Evinizdeki priz kapaklarını değiştirerek yenileyin.",
    "category": "Hızlı & Pratik"
  },
  {
    "text": "Beylikdüzü'nde denize yürüme mesafesinde evler.",
    "category": "Beylikdüzü & Yerel"
  },
  {
    "text": "Gayrimenkul yatırımında yıllık kira artışı.",
    "category": "Yatırım & Kazanç"
  },
  {
    "text": "Emlak piyasasında profesyonel fiyatlandırma.",
    "category": "Piyasa & Haberler"
  },
  {
    "text": "Tapuda işlem öncesi evrak kontrol listesi.",
    "category": "Tüyolar & Hatalar"
  },
  {
    "text": "Ev alırken balkonun güneş alma süresi.",
    "category": "Tüyolar & Hatalar"
  },
  {
    "text": "Evinizdeki kombi ve petek bakımının önemi.",
    "category": "Tüyolar & Hatalar"
  },
  {
    "text": "Gayrimenkulde başarının yolu RE/MAX Kaya'dan geçer.",
    "category": "Tüyolar & Hatalar"
  }
]